{
    "source": "data/LZGCR2X61PX026349.csv",
    "number_of_groups": 225,
    "group_sizes": [
        46,
        21,
        57,
        20,
        234,
        14,
        83,
        273,
        21,
        12,
        19,
        528,
        15,
        121,
        206,
        39,
        29,
        18,
        513,
        78,
        32,
        58,
        51,
        109,
        79,
        13,
        76,
        183,
        37,
        51,
        42,
        178,
        36,
        17,
        20,
        10,
        83,
        18,
        37,
        13,
        142,
        32,
        83,
        18,
        39,
        17,
        73,
        45,
        10,
        18,
        367,
        28,
        17,
        19,
        610,
        18,
        347,
        11,
        47,
        13,
        17,
        29,
        122,
        110,
        58,
        114,
        309,
        24,
        12,
        15,
        11,
        316,
        13,
        559,
        345,
        31,
        10,
        174,
        50,
        154,
        24,
        254,
        68,
        499,
        53,
        99,
        23,
        262,
        138,
        51,
        85,
        39,
        218,
        20,
        37,
        157,
        39,
        15,
        29,
        158,
        118,
        20,
        214,
        48,
        24,
        14,
        58,
        232,
        64,
        170,
        86,
        47,
        16,
        12,
        57,
        61,
        11,
        28,
        70,
        30,
        14,
        18,
        169,
        49,
        21,
        152,
        161,
        71,
        144,
        80,
        111,
        101,
        14,
        148,
        95,
        21,
        122,
        10,
        19,
        69,
        80,
        11,
        27,
        46,
        10,
        114,
        45,
        13,
        216,
        92,
        528,
        25,
        322,
        26,
        423,
        21,
        20,
        13,
        12,
        345,
        92,
        11,
        14,
        91,
        63,
        13,
        257,
        164,
        19,
        302,
        12,
        141,
        170,
        193,
        11,
        48,
        276,
        44,
        343,
        30,
        22,
        17,
        13,
        11,
        12,
        34,
        82,
        68,
        38,
        141,
        121,
        69,
        369,
        37,
        22,
        98,
        11,
        36,
        15,
        15,
        48,
        10,
        13,
        316,
        40,
        337,
        110,
        45,
        55,
        294,
        45,
        17,
        334,
        70,
        123,
        326,
        16,
        76,
        66,
        31,
        224,
        17,
        21,
        162,
        169
    ],
    "correlation_speed_power": 0.768034331527006,
    "results": [
        {
            "model": "linear",
            "full_model_metrics": {
                "mae": 0.011415979645910169,
                "rmse": 0.0157142972387429,
                "r2": 0.8569605256335822,
                "mape": 6.86993011346874,
                "smape": 6.66673448621467
            },
            "full_model_coefficients": {
                "num__speed_mean": 0.00354968206496663,
                "num__power_mean": 0.03572687234455959,
                "cat__road_type_高速": -0.003785475690966987,
                "cat__road_type_国道": 0.0018981276971399565,
                "cat__road_type_省道": 0.0002970660425042028,
                "cat__road_type_其他": 0.0015902819513228333,
                "intercept": 0.19094407156165252
            },
            "relative_importance": {
                "speed": 0.08470593118689701,
                "power": 0.8525490269139826,
                "road_type": 0.06274504189912046
            },
            "hyperparameters": {
                "memory": null,
                "steps": "[('preprocessor', ColumnTransformer(transformers=[('num', StandardScaler(),\n                                 ['speed_mean', 'power_mean']),\n                                ('cat',\n                                 OneHotEncoder(categories=[['高速', '国道', '省道',\n                                                            '其他']],\n                                               handle_unknown='ignore',\n                                               sparse_output=False),\n                                 ['road_type'])])), ('regressor', LinearRegression())]",
                "transform_input": null,
                "verbose": false,
                "preprocessor": "ColumnTransformer(transformers=[('num', StandardScaler(),\n                                 ['speed_mean', 'power_mean']),\n                                ('cat',\n                                 OneHotEncoder(categories=[['高速', '国道', '省道',\n                                                            '其他']],\n                                               handle_unknown='ignore',\n                                               sparse_output=False),\n                                 ['road_type'])])",
                "regressor": "LinearRegression()",
                "preprocessor__force_int_remainder_cols": "deprecated",
                "preprocessor__n_jobs": null,
                "preprocessor__remainder": "drop",
                "preprocessor__sparse_threshold": 0.3,
                "preprocessor__transformer_weights": null,
                "preprocessor__transformers": "[('num', StandardScaler(), ['speed_mean', 'power_mean']), ('cat', OneHotEncoder(categories=[['高速', '国道', '省道', '其他']], handle_unknown='ignore',\n              sparse_output=False), ['road_type'])]",
                "preprocessor__verbose": false,
                "preprocessor__verbose_feature_names_out": true,
                "preprocessor__num": "StandardScaler()",
                "preprocessor__cat": "OneHotEncoder(categories=[['高速', '国道', '省道', '其他']], handle_unknown='ignore',\n              sparse_output=False)",
                "preprocessor__num__copy": true,
                "preprocessor__num__with_mean": true,
                "preprocessor__num__with_std": true,
                "preprocessor__cat__categories": [
                    [
                        "高速",
                        "国道",
                        "省道",
                        "其他"
                    ]
                ],
                "preprocessor__cat__drop": null,
                "preprocessor__cat__dtype": "<class 'numpy.float64'>",
                "preprocessor__cat__feature_name_combiner": "concat",
                "preprocessor__cat__handle_unknown": "ignore",
                "preprocessor__cat__max_categories": null,
                "preprocessor__cat__min_frequency": null,
                "preprocessor__cat__sparse_output": false,
                "regressor__copy_X": true,
                "regressor__fit_intercept": true,
                "regressor__n_jobs": null,
                "regressor__positive": false,
                "regressor__tol": 1e-06
            }
        },
        {
            "model": "ridge",
            "full_model_metrics": {
                "mae": 0.011467299078299565,
                "rmse": 0.015774719150561573,
                "r2": 0.8558584293549852,
                "mape": 6.886379646773329,
                "smape": 6.677598026077057
            },
            "full_model_coefficients": {
                "num__speed_mean": 0.0037702833916404338,
                "num__power_mean": 0.03520344045742985,
                "cat__road_type_高速": -0.0033504037219722897,
                "cat__road_type_国道": 0.0018062439136573185,
                "cat__road_type_省道": 0.00020635165036492667,
                "cat__road_type_其他": 0.0013378081579500246,
                "intercept": 0.19109210792268788
            },
            "relative_importance": {
                "speed": 0.09128636772917471,
                "power": 0.8523481863602901,
                "road_type": 0.05636544591053532
            },
            "hyperparameters": {
                "memory": null,
                "steps": "[('preprocessor', ColumnTransformer(transformers=[('num', StandardScaler(),\n                                 ['speed_mean', 'power_mean']),\n                                ('cat',\n                                 OneHotEncoder(categories=[['高速', '国道', '省道',\n                                                            '其他']],\n                                               handle_unknown='ignore',\n                                               sparse_output=False),\n                                 ['road_type'])])), ('regressor', Ridge())]",
                "transform_input": null,
                "verbose": false,
                "preprocessor": "ColumnTransformer(transformers=[('num', StandardScaler(),\n                                 ['speed_mean', 'power_mean']),\n                                ('cat',\n                                 OneHotEncoder(categories=[['高速', '国道', '省道',\n                                                            '其他']],\n                                               handle_unknown='ignore',\n                                               sparse_output=False),\n                                 ['road_type'])])",
                "regressor": "Ridge()",
                "preprocessor__force_int_remainder_cols": "deprecated",
                "preprocessor__n_jobs": null,
                "preprocessor__remainder": "drop",
                "preprocessor__sparse_threshold": 0.3,
                "preprocessor__transformer_weights": null,
                "preprocessor__transformers": "[('num', StandardScaler(), ['speed_mean', 'power_mean']), ('cat', OneHotEncoder(categories=[['高速', '国道', '省道', '其他']], handle_unknown='ignore',\n              sparse_output=False), ['road_type'])]",
                "preprocessor__verbose": false,
                "preprocessor__verbose_feature_names_out": true,
                "preprocessor__num": "StandardScaler()",
                "preprocessor__cat": "OneHotEncoder(categories=[['高速', '国道', '省道', '其他']], handle_unknown='ignore',\n              sparse_output=False)",
                "preprocessor__num__copy": true,
                "preprocessor__num__with_mean": true,
                "preprocessor__num__with_std": true,
                "preprocessor__cat__categories": [
                    [
                        "高速",
                        "国道",
                        "省道",
                        "其他"
                    ]
                ],
                "preprocessor__cat__drop": null,
                "preprocessor__cat__dtype": "<class 'numpy.float64'>",
                "preprocessor__cat__feature_name_combiner": "concat",
                "preprocessor__cat__handle_unknown": "ignore",
                "preprocessor__cat__max_categories": null,
                "preprocessor__cat__min_frequency": null,
                "preprocessor__cat__sparse_output": false,
                "regressor__alpha": 1.0,
                "regressor__copy_X": true,
                "regressor__fit_intercept": true,
                "regressor__max_iter": null,
                "regressor__positive": false,
                "regressor__random_state": null,
                "regressor__solver": "auto",
                "regressor__tol": 0.0001
            }
        },
        {
            "model": "lasso",
            "full_model_metrics": {
                "mae": 0.034222390259389446,
                "rmse": 0.04275376278999992,
                "r2": -0.058801785232669435,
                "mape": 21.11166711798605,
                "smape": 18.377085556506483
            },
            "full_model_coefficients": {
                "num__speed_mean": 0.0,
                "num__power_mean": 0.0,
                "cat__road_type_高速": 0.0,
                "cat__road_type_国道": 0.0,
                "cat__road_type_省道": 0.0,
                "cat__road_type_其他": -0.0,
                "intercept": 0.20135020217343533
            },
            "relative_importance": null,
            "hyperparameters": {
                "memory": null,
                "steps": "[('preprocessor', ColumnTransformer(transformers=[('num', StandardScaler(),\n                                 ['speed_mean', 'power_mean']),\n                                ('cat',\n                                 OneHotEncoder(categories=[['高速', '国道', '省道',\n                                                            '其他']],\n                                               handle_unknown='ignore',\n                                               sparse_output=False),\n                                 ['road_type'])])), ('regressor', Lasso())]",
                "transform_input": null,
                "verbose": false,
                "preprocessor": "ColumnTransformer(transformers=[('num', StandardScaler(),\n                                 ['speed_mean', 'power_mean']),\n                                ('cat',\n                                 OneHotEncoder(categories=[['高速', '国道', '省道',\n                                                            '其他']],\n                                               handle_unknown='ignore',\n                                               sparse_output=False),\n                                 ['road_type'])])",
                "regressor": "Lasso()",
                "preprocessor__force_int_remainder_cols": "deprecated",
                "preprocessor__n_jobs": null,
                "preprocessor__remainder": "drop",
                "preprocessor__sparse_threshold": 0.3,
                "preprocessor__transformer_weights": null,
                "preprocessor__transformers": "[('num', StandardScaler(), ['speed_mean', 'power_mean']), ('cat', OneHotEncoder(categories=[['高速', '国道', '省道', '其他']], handle_unknown='ignore',\n              sparse_output=False), ['road_type'])]",
                "preprocessor__verbose": false,
                "preprocessor__verbose_feature_names_out": true,
                "preprocessor__num": "StandardScaler()",
                "preprocessor__cat": "OneHotEncoder(categories=[['高速', '国道', '省道', '其他']], handle_unknown='ignore',\n              sparse_output=False)",
                "preprocessor__num__copy": true,
                "preprocessor__num__with_mean": true,
                "preprocessor__num__with_std": true,
                "preprocessor__cat__categories": [
                    [
                        "高速",
                        "国道",
                        "省道",
                        "其他"
                    ]
                ],
                "preprocessor__cat__drop": null,
                "preprocessor__cat__dtype": "<class 'numpy.float64'>",
                "preprocessor__cat__feature_name_combiner": "concat",
                "preprocessor__cat__handle_unknown": "ignore",
                "preprocessor__cat__max_categories": null,
                "preprocessor__cat__min_frequency": null,
                "preprocessor__cat__sparse_output": false,
                "regressor__alpha": 1.0,
                "regressor__copy_X": true,
                "regressor__fit_intercept": true,
                "regressor__max_iter": 1000,
                "regressor__positive": false,
                "regressor__precompute": false,
                "regressor__random_state": null,
                "regressor__selection": "cyclic",
                "regressor__tol": 0.0001,
                "regressor__warm_start": false
            }
        },
        {
            "model": "rf",
            "full_model_metrics": {
                "mae": 0.014573327791337043,
                "rmse": 0.019160375236883322,
                "r2": 0.7873457834822216,
                "mape": 8.830695382818687,
                "smape": 8.49305122219205
            },
            "full_model_coefficients": null,
            "relative_importance": null,
            "hyperparameters": {
                "memory": null,
                "steps": "[('preprocessor', ColumnTransformer(transformers=[('num', StandardScaler(),\n                                 ['speed_mean', 'power_mean']),\n                                ('cat',\n                                 OneHotEncoder(categories=[['高速', '国道', '省道',\n                                                            '其他']],\n                                               handle_unknown='ignore',\n                                               sparse_output=False),\n                                 ['road_type'])])), ('regressor', RandomForestRegressor(random_state=42))]",
                "transform_input": null,
                "verbose": false,
                "preprocessor": "ColumnTransformer(transformers=[('num', StandardScaler(),\n                                 ['speed_mean', 'power_mean']),\n                                ('cat',\n                                 OneHotEncoder(categories=[['高速', '国道', '省道',\n                                                            '其他']],\n                                               handle_unknown='ignore',\n                                               sparse_output=False),\n                                 ['road_type'])])",
                "regressor": "RandomForestRegressor(random_state=42)",
                "preprocessor__force_int_remainder_cols": "deprecated",
                "preprocessor__n_jobs": null,
                "preprocessor__remainder": "drop",
                "preprocessor__sparse_threshold": 0.3,
                "preprocessor__transformer_weights": null,
                "preprocessor__transformers": "[('num', StandardScaler(), ['speed_mean', 'power_mean']), ('cat', OneHotEncoder(categories=[['高速', '国道', '省道', '其他']], handle_unknown='ignore',\n              sparse_output=False), ['road_type'])]",
                "preprocessor__verbose": false,
                "preprocessor__verbose_feature_names_out": true,
                "preprocessor__num": "StandardScaler()",
                "preprocessor__cat": "OneHotEncoder(categories=[['高速', '国道', '省道', '其他']], handle_unknown='ignore',\n              sparse_output=False)",
                "preprocessor__num__copy": true,
                "preprocessor__num__with_mean": true,
                "preprocessor__num__with_std": true,
                "preprocessor__cat__categories": [
                    [
                        "高速",
                        "国道",
                        "省道",
                        "其他"
                    ]
                ],
                "preprocessor__cat__drop": null,
                "preprocessor__cat__dtype": "<class 'numpy.float64'>",
                "preprocessor__cat__feature_name_combiner": "concat",
                "preprocessor__cat__handle_unknown": "ignore",
                "preprocessor__cat__max_categories": null,
                "preprocessor__cat__min_frequency": null,
                "preprocessor__cat__sparse_output": false,
                "regressor__bootstrap": true,
                "regressor__ccp_alpha": 0.0,
                "regressor__criterion": "squared_error",
                "regressor__max_depth": null,
                "regressor__max_features": 1.0,
                "regressor__max_leaf_nodes": null,
                "regressor__max_samples": null,
                "regressor__min_impurity_decrease": 0.0,
                "regressor__min_samples_leaf": 1,
                "regressor__min_samples_split": 2,
                "regressor__min_weight_fraction_leaf": 0.0,
                "regressor__monotonic_cst": null,
                "regressor__n_estimators": 100,
                "regressor__n_jobs": null,
                "regressor__oob_score": false,
                "regressor__random_state": 42,
                "regressor__verbose": 0,
                "regressor__warm_start": false
            }
        },
        {
            "model": "xgboost",
            "full_model_metrics": {
                "mae": 0.016202082029668156,
                "rmse": 0.021089261816661063,
                "r2": 0.7423745667134709,
                "mape": 9.892515543948093,
                "smape": 9.468440665509025
            },
            "full_model_coefficients": null,
            "relative_importance": null,
            "hyperparameters": {
                "memory": null,
                "steps": "[('preprocessor', ColumnTransformer(transformers=[('num', StandardScaler(),\n                                 ['speed_mean', 'power_mean']),\n                                ('cat',\n                                 OneHotEncoder(categories=[['高速', '国道', '省道',\n                                                            '其他']],\n                                               handle_unknown='ignore',\n                                               sparse_output=False),\n                                 ['road_type'])])), ('regressor', XGBRegressor(base_score=None, booster=None, callbacks=None,\n             colsample_bylevel=None, colsample_bynode=None,\n             colsample_bytree=None, device=None, early_stopping_rounds=None,\n             enable_categorical=False, eval_metric=None, feature_types=None,\n             feature_weights=None, gamma=None, grow_policy=None,\n             importance_type=None, interaction_constraints=None,\n             learning_rate=None, max_bin=None, max_cat_threshold=None,\n             max_cat_to_onehot=None, max_delta_step=None, max_depth=None,\n             max_leaves=None, min_child_weight=None, missing=nan,\n             monotone_constraints=None, multi_strategy=None, n_estimators=100,\n             n_jobs=None, num_parallel_tree=None, ...))]",
                "transform_input": null,
                "verbose": false,
                "preprocessor": "ColumnTransformer(transformers=[('num', StandardScaler(),\n                                 ['speed_mean', 'power_mean']),\n                                ('cat',\n                                 OneHotEncoder(categories=[['高速', '国道', '省道',\n                                                            '其他']],\n                                               handle_unknown='ignore',\n                                               sparse_output=False),\n                                 ['road_type'])])",
                "regressor": "XGBRegressor(base_score=None, booster=None, callbacks=None,\n             colsample_bylevel=None, colsample_bynode=None,\n             colsample_bytree=None, device=None, early_stopping_rounds=None,\n             enable_categorical=False, eval_metric=None, feature_types=None,\n             feature_weights=None, gamma=None, grow_policy=None,\n             importance_type=None, interaction_constraints=None,\n             learning_rate=None, max_bin=None, max_cat_threshold=None,\n             max_cat_to_onehot=None, max_delta_step=None, max_depth=None,\n             max_leaves=None, min_child_weight=None, missing=nan,\n             monotone_constraints=None, multi_strategy=None, n_estimators=100,\n             n_jobs=None, num_parallel_tree=None, ...)",
                "preprocessor__force_int_remainder_cols": "deprecated",
                "preprocessor__n_jobs": null,
                "preprocessor__remainder": "drop",
                "preprocessor__sparse_threshold": 0.3,
                "preprocessor__transformer_weights": null,
                "preprocessor__transformers": "[('num', StandardScaler(), ['speed_mean', 'power_mean']), ('cat', OneHotEncoder(categories=[['高速', '国道', '省道', '其他']], handle_unknown='ignore',\n              sparse_output=False), ['road_type'])]",
                "preprocessor__verbose": false,
                "preprocessor__verbose_feature_names_out": true,
                "preprocessor__num": "StandardScaler()",
                "preprocessor__cat": "OneHotEncoder(categories=[['高速', '国道', '省道', '其他']], handle_unknown='ignore',\n              sparse_output=False)",
                "preprocessor__num__copy": true,
                "preprocessor__num__with_mean": true,
                "preprocessor__num__with_std": true,
                "preprocessor__cat__categories": [
                    [
                        "高速",
                        "国道",
                        "省道",
                        "其他"
                    ]
                ],
                "preprocessor__cat__drop": null,
                "preprocessor__cat__dtype": "<class 'numpy.float64'>",
                "preprocessor__cat__feature_name_combiner": "concat",
                "preprocessor__cat__handle_unknown": "ignore",
                "preprocessor__cat__max_categories": null,
                "preprocessor__cat__min_frequency": null,
                "preprocessor__cat__sparse_output": false,
                "regressor__objective": "reg:squarederror",
                "regressor__base_score": null,
                "regressor__booster": null,
                "regressor__callbacks": null,
                "regressor__colsample_bylevel": null,
                "regressor__colsample_bynode": null,
                "regressor__colsample_bytree": null,
                "regressor__device": null,
                "regressor__early_stopping_rounds": null,
                "regressor__enable_categorical": false,
                "regressor__eval_metric": null,
                "regressor__feature_types": null,
                "regressor__feature_weights": null,
                "regressor__gamma": null,
                "regressor__grow_policy": null,
                "regressor__importance_type": null,
                "regressor__interaction_constraints": null,
                "regressor__learning_rate": null,
                "regressor__max_bin": null,
                "regressor__max_cat_threshold": null,
                "regressor__max_cat_to_onehot": null,
                "regressor__max_delta_step": null,
                "regressor__max_depth": null,
                "regressor__max_leaves": null,
                "regressor__min_child_weight": null,
                "regressor__missing": NaN,
                "regressor__monotone_constraints": null,
                "regressor__multi_strategy": null,
                "regressor__n_estimators": 100,
                "regressor__n_jobs": null,
                "regressor__num_parallel_tree": null,
                "regressor__random_state": 42,
                "regressor__reg_alpha": null,
                "regressor__reg_lambda": null,
                "regressor__sampling_method": null,
                "regressor__scale_pos_weight": null,
                "regressor__subsample": null,
                "regressor__tree_method": null,
                "regressor__validate_parameters": null,
                "regressor__verbosity": null
            }
        },
        {
            "model": "lightgbm",
            "full_model_metrics": {
                "mae": 0.014232315676234928,
                "rmse": 0.018724388014884123,
                "r2": 0.7969134122709957,
                "mape": 8.462007529865456,
                "smape": 8.231797279582613
            },
            "full_model_coefficients": null,
            "relative_importance": null,
            "hyperparameters": {
                "memory": null,
                "steps": "[('preprocessor', ColumnTransformer(transformers=[('num', StandardScaler(),\n                                 ['speed_mean', 'power_mean']),\n                                ('cat',\n                                 OneHotEncoder(categories=[['高速', '国道', '省道',\n                                                            '其他']],\n                                               handle_unknown='ignore',\n                                               sparse_output=False),\n                                 ['road_type'])])), ('regressor', LGBMRegressor(random_state=42))]",
                "transform_input": null,
                "verbose": false,
                "preprocessor": "ColumnTransformer(transformers=[('num', StandardScaler(),\n                                 ['speed_mean', 'power_mean']),\n                                ('cat',\n                                 OneHotEncoder(categories=[['高速', '国道', '省道',\n                                                            '其他']],\n                                               handle_unknown='ignore',\n                                               sparse_output=False),\n                                 ['road_type'])])",
                "regressor": "LGBMRegressor(random_state=42)",
                "preprocessor__force_int_remainder_cols": "deprecated",
                "preprocessor__n_jobs": null,
                "preprocessor__remainder": "drop",
                "preprocessor__sparse_threshold": 0.3,
                "preprocessor__transformer_weights": null,
                "preprocessor__transformers": "[('num', StandardScaler(), ['speed_mean', 'power_mean']), ('cat', OneHotEncoder(categories=[['高速', '国道', '省道', '其他']], handle_unknown='ignore',\n              sparse_output=False), ['road_type'])]",
                "preprocessor__verbose": false,
                "preprocessor__verbose_feature_names_out": true,
                "preprocessor__num": "StandardScaler()",
                "preprocessor__cat": "OneHotEncoder(categories=[['高速', '国道', '省道', '其他']], handle_unknown='ignore',\n              sparse_output=False)",
                "preprocessor__num__copy": true,
                "preprocessor__num__with_mean": true,
                "preprocessor__num__with_std": true,
                "preprocessor__cat__categories": [
                    [
                        "高速",
                        "国道",
                        "省道",
                        "其他"
                    ]
                ],
                "preprocessor__cat__drop": null,
                "preprocessor__cat__dtype": "<class 'numpy.float64'>",
                "preprocessor__cat__feature_name_combiner": "concat",
                "preprocessor__cat__handle_unknown": "ignore",
                "preprocessor__cat__max_categories": null,
                "preprocessor__cat__min_frequency": null,
                "preprocessor__cat__sparse_output": false,
                "regressor__boosting_type": "gbdt",
                "regressor__class_weight": null,
                "regressor__colsample_bytree": 1.0,
                "regressor__importance_type": "split",
                "regressor__learning_rate": 0.1,
                "regressor__max_depth": -1,
                "regressor__min_child_samples": 20,
                "regressor__min_child_weight": 0.001,
                "regressor__min_split_gain": 0.0,
                "regressor__n_estimators": 100,
                "regressor__n_jobs": null,
                "regressor__num_leaves": 31,
                "regressor__objective": null,
                "regressor__random_state": 42,
                "regressor__reg_alpha": 0.0,
                "regressor__reg_lambda": 0.0,
                "regressor__subsample": 1.0,
                "regressor__subsample_for_bin": 200000,
                "regressor__subsample_freq": 0
            }
        },
        {
            "model": "polynomial",
            "full_model_metrics": {
                "mae": 0.010980152849290927,
                "rmse": 0.01569975205185931,
                "r2": 0.8572251983682999,
                "mape": 6.680301916509189,
                "smape": 6.4473318104457125
            },
            "full_model_coefficients": null,
            "relative_importance": null,
            "hyperparameters": {
                "memory": null,
                "steps": "[('preprocessor', ColumnTransformer(transformers=[('num', StandardScaler(),\n                                 ['speed_mean', 'power_mean']),\n                                ('cat',\n                                 OneHotEncoder(categories=[['高速', '国道', '省道',\n                                                            '其他']],\n                                               handle_unknown='ignore',\n                                               sparse_output=False),\n                                 ['road_type'])])), ('poly', PolynomialFeatures(include_bias=False)), ('regressor', LinearRegression())]",
                "transform_input": null,
                "verbose": false,
                "preprocessor": "ColumnTransformer(transformers=[('num', StandardScaler(),\n                                 ['speed_mean', 'power_mean']),\n                                ('cat',\n                                 OneHotEncoder(categories=[['高速', '国道', '省道',\n                                                            '其他']],\n                                               handle_unknown='ignore',\n                                               sparse_output=False),\n                                 ['road_type'])])",
                "poly": "PolynomialFeatures(include_bias=False)",
                "regressor": "LinearRegression()",
                "preprocessor__force_int_remainder_cols": "deprecated",
                "preprocessor__n_jobs": null,
                "preprocessor__remainder": "drop",
                "preprocessor__sparse_threshold": 0.3,
                "preprocessor__transformer_weights": null,
                "preprocessor__transformers": "[('num', StandardScaler(), ['speed_mean', 'power_mean']), ('cat', OneHotEncoder(categories=[['高速', '国道', '省道', '其他']], handle_unknown='ignore',\n              sparse_output=False), ['road_type'])]",
                "preprocessor__verbose": false,
                "preprocessor__verbose_feature_names_out": true,
                "preprocessor__num": "StandardScaler()",
                "preprocessor__cat": "OneHotEncoder(categories=[['高速', '国道', '省道', '其他']], handle_unknown='ignore',\n              sparse_output=False)",
                "preprocessor__num__copy": true,
                "preprocessor__num__with_mean": true,
                "preprocessor__num__with_std": true,
                "preprocessor__cat__categories": [
                    [
                        "高速",
                        "国道",
                        "省道",
                        "其他"
                    ]
                ],
                "preprocessor__cat__drop": null,
                "preprocessor__cat__dtype": "<class 'numpy.float64'>",
                "preprocessor__cat__feature_name_combiner": "concat",
                "preprocessor__cat__handle_unknown": "ignore",
                "preprocessor__cat__max_categories": null,
                "preprocessor__cat__min_frequency": null,
                "preprocessor__cat__sparse_output": false,
                "poly__degree": 2,
                "poly__include_bias": false,
                "poly__interaction_only": false,
                "poly__order": "C",
                "regressor__copy_X": true,
                "regressor__fit_intercept": true,
                "regressor__n_jobs": null,
                "regressor__positive": false,
                "regressor__tol": 1e-06
            }
        },
        {
            "model": "gam",
            "full_model_metrics": {
                "mae": 0.011022242319496443,
                "rmse": 0.015879759270499054,
                "r2": 0.853932429060687,
                "mape": 6.7131785284863925,
                "smape": 6.469432986152898
            },
            "full_model_coefficients": null,
            "relative_importance": null,
            "hyperparameters": {
                "scale": null,
                "max_iter": 100,
                "tol": 0.0001,
                "callbacks": "[Deviance(), Diffs()]",
                "verbose": false,
                "terms": "s(0) + s(1) + f(2) + intercept",
                "fit_intercept": true
            }
        }
    ]
}